README.md
setup.py
leedMx_distributions/Binomialdistribution.py
leedMx_distributions/Gaussiandistribution.py
leedMx_distributions/Generaldistribution.py
leedMx_distributions/__init__.py
leedMx_distributions.egg-info/PKG-INFO
leedMx_distributions.egg-info/SOURCES.txt
leedMx_distributions.egg-info/dependency_links.txt
leedMx_distributions.egg-info/not-zip-safe
leedMx_distributions.egg-info/top_level.txt