Metadata-Version: 1.0
Name: leedMx-distributions
Version: 0.1
Summary: Gaussian and Binomial distributions
Home-page: UNKNOWN
Author: UNKNOWN
Author-email: esparza.mexico@gmail.com
License: UNKNOWN
Platform: UNKNOWN
